Workbook

Sheet Assumptions
A1: Riverside Malls — Smart Trolley Pilot
A2: Inputs (blue) drive every formula on the other sheets.
A4: Assumption | B4: Value | C4: Note
A5: Variable cost per trolley (£/mo) | B5: 40 | C5: Maintenance, support, telematics
A6: Fixed cost per month (£) | B6: 3000 | C6: Platform, depot, on-call staff
A7: Number of trolleys in pilot | B7: 25 | C7: Phase-1 fleet size
A8: Price tier 1 — floor (£) | B8: 150 | C8: Penetration price
A9: Price tier 2 — base (£) | B9: 200 | C9: Headline pilot price
A10: Price tier 3 — premium (£) | B10: 250 | C10: Stretch price
A11: Price tier 4 — aspirational (£) | B11: 300 | C11: Upside price
A12: Churn rate (stretch, monthly) | B12: 0.2 | C12: Trolleys needing re-deployment
A13: Re-deployment cost per churned trolley (£) | B13: 120 | C13: Pickup + refurb + logistics
A14: Support cost multiplier (stretch) | B14: 2 | C14: 2× = stressed scenario

Sheet PriceTiers
A1: Profit & Break-even at the 4 Candidate Prices
A3: Price tier | B3: Price (£) | C3: Contribution (£) | D3: Monthly profit (£) | E3: Break-even trolleys
A4: Floor (£150) | B4: =Assumptions!$B$8 | C4: =B4-Assumptions!$B$5 | D4: =Assumptions!$B$7*C4-Assumptions!$B$6 | E4: =Assumptions!$B$6/C4
A5: Base (£200) | B5: =Assumptions!$B$9 | C5: =B5-Assumptions!$B$5 | D5: =Assumptions!$B$7*C5-Assumptions!$B$6 | E5: =Assumptions!$B$6/C5
A6: Premium (£250) | B6: =Assumptions!$B$10 | C6: =B6-Assumptions!$B$5 | D6: =Assumptions!$B$7*C6-Assumptions!$B$6 | E6: =Assumptions!$B$6/C6
A7: Aspirational (£300) | B7: =Assumptions!$B$11 | C7: =B7-Assumptions!$B$5 | D7: =Assumptions!$B$7*C7-Assumptions!$B$6 | E7: =Assumptions!$B$6/C7
A9: Recommendation: | B9: Charge £200/trolley/month. £1,000/month profit, 6-trolley margin of safety above the 18.75 break-even.

Sheet Sensitivity
A1: Sensitivity — How much margin can we lose before the pilot breaks?
A3: Scenario | B3: Variable cost (£) | C3: Fixed cost (£) | D3: Effective trolleys | E3: Monthly profit (£) @ £200
A4: Baseline | B4: =Assumptions!$B$5 | C4: =Assumptions!$B$6 | D4: =Assumptions!$B$7 | E4: =D4*(Assumptions!$B$9-B4)-C4
A5: Support cost doubles | B5: =Assumptions!$B$5*Assumptions!$B$14 | C5: =Assumptions!$B$6 | D5: =Assumptions!$B$7 | E5: =D5*(Assumptions!$B$9-B5)-C5
A6: 20% monthly churn (re-deployment cost) | B6: =Assumptions!$B$5 | C6: =Assumptions!$B$6+Assumptions!$B$12*Assumptions!$B$7*Assumptions!$B$13 | D6: =Assumptions!$B$7*(1-Assumptions!$B$12) | E6: =D6*(Assumptions!$B$9-B6)-C6
A8: Read: at £200, the pilot survives 2× support cost exactly at break-even. It does NOT survive 20% monthly churn.

Sheet ProfitCurve
A1: Full Price Sweep — for profit-vs-price chart
A3: Price (£) | B3: Monthly profit (£) | C3: Break-even trolleys
A4: 100 | B4: =Assumptions!$B$7*(A4-Assumptions!$B$5)-Assumptions!$B$6 | C4: =Assumptions!$B$6/(A4-Assumptions!$B$5)
A5: 110 | B5: =Assumptions!$B$7*(A5-Assumptions!$B$5)-Assumptions!$B$6 | C5: =Assumptions!$B$6/(A5-Assumptions!$B$5)
A6: 120 | B6: =Assumptions!$B$7*(A6-Assumptions!$B$5)-Assumptions!$B$6 | C6: =Assumptions!$B$6/(A6-Assumptions!$B$5)
A7: 130 | B7: =Assumptions!$B$7*(A7-Assumptions!$B$5)-Assumptions!$B$6 | C7: =Assumptions!$B$6/(A7-Assumptions!$B$5)
A8: 140 | B8: =Assumptions!$B$7*(A8-Assumptions!$B$5)-Assumptions!$B$6 | C8: =Assumptions!$B$6/(A8-Assumptions!$B$5)
A9: 150 | B9: =Assumptions!$B$7*(A9-Assumptions!$B$5)-Assumptions!$B$6 | C9: =Assumptions!$B$6/(A9-Assumptions!$B$5)
A10: 160 | B10: =Assumptions!$B$7*(A10-Assumptions!$B$5)-Assumptions!$B$6 | C10: =Assumptions!$B$6/(A10-Assumptions!$B$5)
A11: 170 | B11: =Assumptions!$B$7*(A11-Assumptions!$B$5)-Assumptions!$B$6 | C11: =Assumptions!$B$6/(A11-Assumptions!$B$5)
A12: 180 | B12: =Assumptions!$B$7*(A12-Assumptions!$B$5)-Assumptions!$B$6 | C12: =Assumptions!$B$6/(A12-Assumptions!$B$5)
A13: 190 | B13: =Assumptions!$B$7*(A13-Assumptions!$B$5)-Assumptions!$B$6 | C13: =Assumptions!$B$6/(A13-Assumptions!$B$5)
A14: 200 | B14: =Assumptions!$B$7*(A14-Assumptions!$B$5)-Assumptions!$B$6 | C14: =Assumptions!$B$6/(A14-Assumptions!$B$5)
A15: 210 | B15: =Assumptions!$B$7*(A15-Assumptions!$B$5)-Assumptions!$B$6 | C15: =Assumptions!$B$6/(A15-Assumptions!$B$5)
... A29: 350 | B29: =Assumptions!$B$7*(A29-Assumptions!$B$5)-Assumptions!$B$6 | C29: =Assumptions!$B$6/(A29-Assumptions!$B$5)
